_zkapauthorizer/__init__.py
_zkapauthorizer/_base64.py
_zkapauthorizer/_json.py
_zkapauthorizer/_plugin.py
_zkapauthorizer/_stack.py
_zkapauthorizer/_storage_client.py
_zkapauthorizer/_storage_server.py
_zkapauthorizer/_types.py
_zkapauthorizer/api.py
_zkapauthorizer/backup-recovery.yaml
_zkapauthorizer/config.py
_zkapauthorizer/configutil.py
_zkapauthorizer/controller.py
_zkapauthorizer/eliot.py
_zkapauthorizer/foolscap.py
_zkapauthorizer/lease_maintenance.py
_zkapauthorizer/model.py
_zkapauthorizer/pricecalculator.py
_zkapauthorizer/private.py
_zkapauthorizer/recover.py
_zkapauthorizer/replicate.py
_zkapauthorizer/resource.py
_zkapauthorizer/schema.py
_zkapauthorizer/spending.py
_zkapauthorizer/sql.py
_zkapauthorizer/storage_common.py
_zkapauthorizer/tahoe.py
_zkapauthorizer/validators.py
_zkapauthorizer/server/__init__.py
_zkapauthorizer/server/spending.py
_zkapauthorizer/tests/__init__.py
_zkapauthorizer/tests/_exception.py
_zkapauthorizer/tests/_float_matchers.py
_zkapauthorizer/tests/_sql_matchers.py
_zkapauthorizer/tests/common.py
_zkapauthorizer/tests/fixtures.py
_zkapauthorizer/tests/foolscap.py
_zkapauthorizer/tests/json.py
_zkapauthorizer/tests/matchers.py
_zkapauthorizer/tests/privacypass.py
_zkapauthorizer/tests/resources.py
_zkapauthorizer/tests/storage_common.py
_zkapauthorizer/tests/strategies.py
_zkapauthorizer/tests/test_base64.py
_zkapauthorizer/tests/test_client_resource.py
_zkapauthorizer/tests/test_controller.py
_zkapauthorizer/tests/test_foolscap.py
_zkapauthorizer/tests/test_lease_maintenance.py
_zkapauthorizer/tests/test_matchers.py
_zkapauthorizer/tests/test_model.py
_zkapauthorizer/tests/test_plugin.py
_zkapauthorizer/tests/test_pricecalculator.py
_zkapauthorizer/tests/test_private.py
_zkapauthorizer/tests/test_recover.py
_zkapauthorizer/tests/test_replicate.py
_zkapauthorizer/tests/test_schema.py
_zkapauthorizer/tests/test_spending.py
_zkapauthorizer/tests/test_sql.py
_zkapauthorizer/tests/test_storage_client.py
zero_knowledge_access_pass_authorizer-2022.8.21.dist-info/LICENSE-2.0.txt
zero_knowledge_access_pass_authorizer-2022.8.21.dist-info/METADATA
zero_knowledge_access_pass_authorizer-2022.8.21.dist-info/WHEEL
zero_knowledge_access_pass_authorizer-2022.8.21.dist-info/top_level.txt
zero_knowledge_access_pass_authorizer-2022.8.21.dist-info/RECORD
