Metadata-Version: 2.1
Name: zero-knowledge-access-pass-authorizer
Version: 2022.8.21
Summary: A `Tahoe-LAFS`_ storage-system plugin which authorizes storage operations based on privacy-respecting tokens.
Home-page: https://private.storage/
Author: PrivateStorage.io Inc.
Author-email: support@private.storage
Maintainer: PrivateStorage.io Inc.
License: Apache 2.0
Keywords: tahoe-lafs,storage,privacy,cryptography
Platform: POSIX
Classifier: Framework :: Twisted
Classifier: Programming Language :: Python :: 3
Classifier: Programming Language :: Python :: 3.9
License-File: LICENSE-2.0.txt
Requires-Dist: attrs
Requires-Dist: zope.interface
Requires-Dist: eliot (>=1.11)
Requires-Dist: aniso8601
Requires-Dist: compose (~=1.0)
Requires-Dist: python-challenge-bypass-ristretto
Requires-Dist: Twisted[conch,tls] (>=19.10.0)
Requires-Dist: tahoe-lafs (<1.18.1,>=1.17.1)
Requires-Dist: treq
Requires-Dist: pyutil
Requires-Dist: prometheus-client
Requires-Dist: colorama
Requires-Dist: sqlparse
Requires-Dist: cbor2
Requires-Dist: autobahn (!=22.4.1,!=22.4.2,!=22.5.1,>=21.11.1)
